{
  "ver": "1.0.0",
  "nam": {
    "fn": "Μάριος",
    "fnt": "MARIOS",
    "gn": "Μενεξές",
    "gnt": "MENEKSES"
  },
  "dob": "1959-10-12",
  "v": [
    {
      "tg": "840539006",
      "vp": "J07BX03",
      "mp": "EU/1/20/1528",
      "ma": "ORG-100030215",
      "dn": 1,
      "sd": 2,
      "dt": "2021-01-21",
      "co": "GR",
      "is": "Ministry of Health",
      "ci": "urn:uvci:01:GR:78J239D6#2"
    },
    {
      "tg": "840539006",
      "vp": "J07BX03",
      "mp": "EU/1/20/1528",
      "ma": "ORG-100030215",
      "dn": 2,
      "sd": 2,
      "dt": "2021-02-21",
      "co": "GR",
      "is": "Ministry of Health",
      "ci": "urn:uvci:01:GR:78J239D6#2"
    }
  ]
}
